lcov/__about__.py
lcov/__config__.py
lcov/__init__.py
lcov/gendesc.py
lcov/genpng.py
lcov/lcov.cfg
lcov/lcov.py
lcov/types.py
lcov/util.py
lcov-1.15.5a0.dist-info/LICENSE
lcov-1.15.5a0.dist-info/METADATA
lcov-1.15.5a0.dist-info/WHEEL
lcov-1.15.5a0.dist-info/entry_points.txt
lcov-1.15.5a0.dist-info/top_level.txt
lcov-1.15.5a0.dist-info/zip-safe
lcov-1.15.5a0.dist-info/RECORD
