Metadata-Version: 2.1
Name: lcov
Version: 1.15.5a0
Summary: Python port of the lcov utility.
Home-page: https://pypi.org/project/lcov/
Author: Adam Karpierz
Author-email: adam@karpierz.net
Maintainer: Adam Karpierz
Maintainer-email: adam@karpierz.net
License: BSD license ; https://opensource.org/licenses/BSD-3-Clause
Download-URL: https://pypi.org/project/lcov/
Project-URL: Documentation, https://lcov.readthedocs.io/
Project-URL: Source, https://github.com/karpierz/lcov
Project-URL: Issues, https://github.com/karpierz/lcov/issues
Keywords: lcov,gcov,gcovr,coverage,gcc,Jenkins,Cobertura
Platform: any
Classifier: Development Status :: 2 - Pre-Alpha
Classifier: Intended Audience :: Developers
Classifier: License :: OSI Approved :: BSD License
Classifier: Operating System :: OS Independent
Classifier: Natural Language :: Polish
Classifier: Programming Language :: Python
Classifier: Programming Language :: Python :: 3
Classifier: Programming Language :: Python :: 3.6
Classifier: Programming Language :: Python :: 3.7
Classifier: Programming Language :: Python :: 3.8
Classifier: Programming Language :: Python :: 3.9
Classifier: Programming Language :: Python :: 3 :: Only
Classifier: Programming Language :: Python :: Implementation :: CPython
Classifier: Programming Language :: Python :: Implementation :: Stackless
Classifier: Topic :: Software Development :: Quality Assurance
Classifier: Topic :: Software Development :: Testing
Classifier: Topic :: Utilities
Requires-Python: <4.0.0,>=3.7.0
License-File: LICENSE
Requires-Dist: setuptools (>=42.0.2)
Requires-Dist: packaging (>=21.2.0)
Requires-Dist: importlib-resources (>=5.4.0)
Requires-Dist: importlib-metadata (>=4.7.1)
Requires-Dist: pkg-about (>=1.0.3)
Requires-Dist: atpublic (>=2.3.0)
Provides-Extra: doc
Requires-Dist: Sphinx (>=4.2.0) ; extra == 'doc'
Requires-Dist: sphinx-tabs (>=3.2.0) ; extra == 'doc'
Requires-Dist: sphinxcontrib-spelling (>=7.2.1) ; extra == 'doc'
Requires-Dist: restructuredtext-lint (>=1.3.2) ; extra == 'doc'
Provides-Extra: test
Requires-Dist: deepdiff (>=5.6.0) ; extra == 'test'
